interpret_segmentation/hdm/__init__.py
interpret_segmentation/hdm/hdm_test.py
interpret_segmentation/rise/__init__.py
interpret_segmentation-1.0.0.dist-info/LICENSE
interpret_segmentation-1.0.0.dist-info/METADATA
interpret_segmentation-1.0.0.dist-info/WHEEL
interpret_segmentation-1.0.0.dist-info/top_level.txt
interpret_segmentation-1.0.0.dist-info/RECORD
